MANIFEST.in
README.md
setup.py
AssetStudioPy/AssetsManager.py
AssetStudioPy/ObjectReader.py
AssetStudioPy/__init__.py
AssetStudioPy/_load.py
AssetStudioPy/_version.py
AssetStudioPy/export.py
AssetStudioPy/runtimeconfig.json
AssetStudioPy/settings.py
AssetStudioPy/update.py
AssetStudioPy.egg-info/PKG-INFO
AssetStudioPy.egg-info/SOURCES.txt
AssetStudioPy.egg-info/dependency_links.txt
AssetStudioPy.egg-info/requires.txt
AssetStudioPy.egg-info/top_level.txt
AssetStudioPy/AssetStudioUtility/AssetStudio.PInvoke.dll
AssetStudioPy/AssetStudioUtility/AssetStudio.dll
AssetStudioPy/AssetStudioUtility/AssetStudioFBXNative.dll
AssetStudioPy/AssetStudioUtility/AssetStudioFBXNative.lib
AssetStudioPy/AssetStudioUtility/AssetStudioFBXWrapper.dll
AssetStudioPy/AssetStudioUtility/AssetStudioUtility.dll
AssetStudioPy/AssetStudioUtility/K4os.Compression.LZ4.dll
AssetStudioPy/AssetStudioUtility/Mono.Cecil.Mdb.dll
AssetStudioPy/AssetStudioUtility/Mono.Cecil.Pdb.dll
AssetStudioPy/AssetStudioUtility/Mono.Cecil.Rocks.dll
AssetStudioPy/AssetStudioUtility/Mono.Cecil.dll
AssetStudioPy/AssetStudioUtility/SixLabors.Fonts.dll
AssetStudioPy/AssetStudioUtility/SixLabors.ImageSharp.Drawing.dll
AssetStudioPy/AssetStudioUtility/SixLabors.ImageSharp.dll
AssetStudioPy/AssetStudioUtility/Texture2DDecoderNative.dll
AssetStudioPy/AssetStudioUtility/Texture2DDecoderNative.lib
AssetStudioPy/AssetStudioUtility/Texture2DDecoderWrapper.dll
AssetStudioPy/AssetStudioUtility/fmod.dll